stat_guard/__init__.py
stat_guard/api.py
stat_guard/engine.py
stat_guard/policy.py
stat_guard/report.py
stat_guard/violations.py
stat_guard/checks/base.py
stat_guard/checks/distribution.py
stat_guard/checks/sample_size.py
stat_guard/checks/unit_integrity.py
stat_guard-0.2.0.dist-info/licenses/LICENSE
stat_guard-0.2.0.dist-info/METADATA
stat_guard-0.2.0.dist-info/WHEEL
stat_guard-0.2.0.dist-info/top_level.txt
stat_guard-0.2.0.dist-info/RECORD
