Metadata-Version: 2.4
Name: stat-guard
Version: 0.2.0
Summary: Prevent statistically invalid analyses from being shipped
Author-email: Aaryan Solanki <aryan.solanki.stats@gmail.com>
License: MIT
Project-URL: Homepage, https://github.com/aaryansolankii/stat-guard
Project-URL: Repository, https://github.com/aaryansolankii/stat-guard
Project-URL: Issues, https://github.com/aaryansolankii/stat-guard/issues
Keywords: statistics,validation,experiments,ab-testing,data-quality
Classifier: Development Status :: 3 - Alpha
Classifier: Intended Audience :: Developers
Classifier: Intended Audience :: Science/Research
Classifier: Topic :: Scientific/Engineering :: Mathematics
Classifier: License :: OSI Approved :: MIT License
Classifier: Programming Language :: Python :: 3
Classifier: Programming Language :: Python :: 3.8
Classifier: Programming Language :: Python :: 3.9
Classifier: Programming Language :: Python :: 3.10
Classifier: Programming Language :: Python :: 3.11
Classifier: Programming Language :: Python :: 3.12
Requires-Python: >=3.8
License-File: LICENSE
Requires-Dist: pandas>=1.3.0
Requires-Dist: numpy>=1.20.0
Requires-Dist: scipy>=1.7.0
Provides-Extra: dev
Requires-Dist: pytest>=7.0; extra == "dev"
Requires-Dist: pytest-cov>=3.0; extra == "dev"
Requires-Dist: black>=22.0; extra == "dev"
Requires-Dist: flake8>=4.0; extra == "dev"
Requires-Dist: mypy>=0.950; extra == "dev"
Dynamic: license-file
